condor/__init__.py
condor/config.py
condor/dbutil.py
condor/normalize.py
condor/util.py
condor/models/__init__.py
condor/models/base.py
condor/models/bibliography.py
condor/models/document.py
condor/models/query.py
condor/models/ranking_matrix.py
condor/models/term_document_matrix.py
condor/record/__init__.py
condor/record/base.py
condor/record/bib.py
condor/record/froac.py
condor/record/isi.py
condor/scripts/__init__.py
condor/scripts/bibliography.py
condor/scripts/cli.py
condor/scripts/contributor.py
condor/scripts/evaluate.py
condor/scripts/matrix.py
condor/scripts/model.py
condor/scripts/query.py
condor/scripts/ranking.py
condor/scripts/utils.py
condor_ir-1.2.2.dist-info/LICENSE.txt
condor_ir-1.2.2.dist-info/METADATA
condor_ir-1.2.2.dist-info/WHEEL
condor_ir-1.2.2.dist-info/entry_points.txt
condor_ir-1.2.2.dist-info/top_level.txt
condor_ir-1.2.2.dist-info/RECORD
