Metadata-Version: 2.1
Name: condor-ir
Version: 1.2.2
Summary: A latent semantic search engine implementation
Home-page: https://condor-ir.co
Author: Oscar D. Arbeláez-Echeverri <@odarbelaeze>, German A. Osorio-Zuluaga
Author-email: odarbelaeze@gmail.com
License: UNKNOWN
Download-URL: https://github.com/odarbelaeze/condor-ir/tarball/1.2.2
Keywords: lsa,search,search engine,semantics
Platform: UNKNOWN
Requires-Dist: SQLAlchemy (~=1.3)
Requires-Dist: bibtexparser (~=0.6.2)
Requires-Dist: click (~=6.7)
Requires-Dist: nltk (~=3.4)
Requires-Dist: numpy (~=1.17)
Requires-Dist: langdetect
Requires-Dist: langcodes
Requires-Dist: PyPDF2 (~=1.26)
Requires-Dist: tabulate (~=0.7)
Requires-Dist: tqdm (~=4.11.2)
Requires-Dist: requests (<3,>2)
Provides-Extra: mysql
Requires-Dist: mysqlclient ; extra == 'mysql'
Provides-Extra: postgres
Requires-Dist: psycopg2 ; extra == 'postgres'
